dash_ag_grid/AgGrid.py
dash_ag_grid/__init__.py
dash_ag_grid/_imports_.py
dash_ag_grid/async-community.js
dash_ag_grid/async-community.js.map
dash_ag_grid/async-enterprise.js
dash_ag_grid/async-enterprise.js.map
dash_ag_grid/dash_ag_grid.min.js
dash_ag_grid/dash_ag_grid.min.js.map
dash_ag_grid/metadata.json
dash_ag_grid/package-info.json
dash_ag_grid-32.3.4.dist-info/licenses/LICENSE
dash_ag_grid-32.3.4.dist-info/METADATA
dash_ag_grid-32.3.4.dist-info/WHEEL
dash_ag_grid-32.3.4.dist-info/top_level.txt
dash_ag_grid-32.3.4.dist-info/RECORD
