Metadata-Version: 2.4
Name: dash_ag_grid
Version: 32.3.4
Summary: Dash wrapper around AG Grid, the best interactive data grid for the web.
Home-page: https://dash.plotly.com/dash-ag-grid
Author: Plotly <chris@plot.ly>
License: MIT
Project-URL: Documentation, https://dash.plotly.com/dash-ag-grid
Project-URL: Source, https://github.com/plotly/dash-ag-grid
Project-URL: Issue Tracker, https://github.com/plotly/dash-ag-grid/issues
Classifier: Framework :: Dash
Classifier: License :: OSI Approved :: MIT License
Classifier: Programming Language :: Python
Classifier: Programming Language :: Python :: 3
Classifier: Programming Language :: Python :: 3.6
Classifier: Programming Language :: Python :: 3.7
Classifier: Programming Language :: Python :: 3.8
Classifier: Programming Language :: Python :: 3.9
Classifier: Programming Language :: Python :: 3.10
Classifier: Programming Language :: Python :: 3.11
Requires-Python: >=3.6
License-File: LICENSE
Requires-Dist: dash>=2
Provides-Extra: dev
Requires-Dist: dash[ci,dev,testing]>=2.0; extra == "dev"
Requires-Dist: dash_mantine_components==0.12.1; extra == "dev"
Requires-Dist: pyyaml>=5.0; extra == "dev"
Requires-Dist: pytest<8.1.0; extra == "dev"
Requires-Dist: wheel; extra == "dev"
Requires-Dist: selenium<4.3.0,>=4.0.0; extra == "dev"
Provides-Extra: docs
Requires-Dist: dash>=2.9.0; extra == "docs"
Requires-Dist: gunicorn>=19.9.0; extra == "docs"
Requires-Dist: pandas>=1.2.3; extra == "docs"
Requires-Dist: pyyaml>=6.0; extra == "docs"
Requires-Dist: dash-bootstrap-components>=1.0.0; extra == "docs"
Requires-Dist: yfinance; extra == "docs"
Requires-Dist: dash-mantine-components; extra == "docs"
Requires-Dist: dash-iconify; extra == "docs"
Requires-Dist: colorlover; extra == "docs"
Requires-Dist: statsmodels; extra == "docs"
Dynamic: author
Dynamic: classifier
Dynamic: description
Dynamic: description-content-type
Dynamic: home-page
Dynamic: license
Dynamic: license-file
Dynamic: project-url
Dynamic: provides-extra
Dynamic: requires-dist
Dynamic: requires-python
Dynamic: summary
